sensory/__init__.py
sensory-0.3.0.dist-info/METADATA
sensory-0.3.0.dist-info/WHEEL
sensory-0.3.0.dist-info/RECORD
