Metadata-Version: 2.4
Name: sensory
Version: 0.3.0
Summary: Multi-Sensory AI Communication - Morse, Braille, SSTV/REFLUX encode+decode. Complete sensory loop!
Project-URL: Homepage, https://humotica.com
Author-email: Jasper van de Meent <jasper@humotica.com>, Root AI <root_ai@humotica.nl>
License-Expression: AGPL-3.0-or-later
Keywords: ai-communication,braille,humotica,morse,multimodal,off-grid,reflux,sensory,sstv
Classifier: Development Status :: 3 - Alpha
Classifier: Intended Audience :: Developers
Classifier: License :: OSI Approved :: GNU Affero General Public License v3 or later (AGPLv3+)
Classifier: Programming Language :: Python :: 3
Classifier: Topic :: Communications
Requires-Python: >=3.10
Requires-Dist: mcp-server-sensory>=0.3.0
